adc_sdk/__init__.py
adc_sdk/cli.py
adc_sdk/client.py
adc_sdk/exceptions.py
adc_sdk/queries.py
adc_sdk/raw_queries.py
adc_sdk-0.1.3.dist-info/entry_points.txt
adc_sdk-0.1.3.dist-info/LICENSE
adc_sdk-0.1.3.dist-info/WHEEL
adc_sdk-0.1.3.dist-info/METADATA
adc_sdk-0.1.3.dist-info/RECORD
