Metadata-Version: 2.1
Name: adc-sdk
Version: 0.1.3
Summary: Argonne Discovery Cloud SDK and CLI
License: LICENSE
Author: Argonne National Laboratory
Author-email: discovery@anl.gov
Requires-Python: >=3.7,<4.0
Classifier: License :: Other/Proprietary License
Classifier: Programming Language :: Python :: 3
Classifier: Programming Language :: Python :: 3.7
Classifier: Programming Language :: Python :: 3.8
Classifier: Programming Language :: Python :: 3.9
Requires-Dist: aiohttp (>=3.7.4,<4.0.0)
Requires-Dist: gql (==3.0.0a6)
Requires-Dist: requests (>=2.26.0,<3.0.0)
Requires-Dist: typer (>=0.3.2,<0.4.0)
Requires-Dist: websockets (>=9.1,<10.0)
